masoud/__init__.py
masoud/_cli.py
masoud/_docker.py
masoud/_inventory.py
masoud/_logging.py
masoud/_service.py
masoud-1.5.0.dist-info/METADATA
masoud-1.5.0.dist-info/WHEEL
masoud-1.5.0.dist-info/licenses/LICENSE
masoud-1.5.0.dist-info/RECORD
