Metadata-Version: 2.1
Name: masoud
Version: 1.5.0
Summary: Think Docker Compose + Ansible inventory + Python-scriptable
Author-email: satoqz <mail@satoqz.net>
License-File: LICENSE
Requires-Python: >=3.12
Requires-Dist: click>=8.1.7
